marketsim/__init__.py
marketsim/keyed_heap.py
marketsim/market.py
tests/__init__.py
tests/test_allocation.py
tests/test_keyed_heap.py
tests/test_market.py
tests/test_order.py
tests/test_order_book.py
marketsim-0.0.1.dist-info/LICENSE
marketsim-0.0.1.dist-info/METADATA
marketsim-0.0.1.dist-info/WHEEL
marketsim-0.0.1.dist-info/top_level.txt
marketsim-0.0.1.dist-info/RECORD
